langchain_linkup/__init__.py
langchain_linkup/py.typed
langchain_linkup/search_retriever.py
langchain_linkup/search_tool.py
langchain_linkup-0.1.7.dist-info/METADATA
langchain_linkup-0.1.7.dist-info/WHEEL
langchain_linkup-0.1.7.dist-info/licenses/LICENSE
langchain_linkup-0.1.7.dist-info/RECORD
