Metadata-Version: 2.4
Name: langchain-linkup
Version: 0.1.7
Summary: A Langchain integration for the Linkup API
Project-URL: Homepage, https://github.com/LinkupPlatform/langchain-linkup
Project-URL: Documentation, https://github.com/LinkupPlatform/langchain-linkup#readme
Project-URL: Source, https://github.com/LinkupPlatform/langchain-linkup
Project-URL: Tracker, https://github.com/LinkupPlatform/langchain-linkup/issues
Author-email: LINKUP TECHNOLOGIES <contact@linkup.so>
License-Expression: MIT
License-File: LICENSE
Keywords: api,integration,langchain,linkup,retriever,search
Classifier: Intended Audience :: Developers
Classifier: License :: OSI Approved :: MIT License
Classifier: Operating System :: OS Independent
Classifier: Topic :: Software Development :: Libraries :: Python Modules
Requires-Python: <4.0,>=3.9
Requires-Dist: langchain-core
Requires-Dist: linkup-sdk>=0.2.8
